gref4hsi/__init__.py
gref4hsi/scripts/__init__.py
gref4hsi/scripts/coregistration.py
gref4hsi/scripts/georeference.py
gref4hsi/scripts/georeference.py.orig
gref4hsi/scripts/orthorectification.py
gref4hsi/tests/__init__.py
gref4hsi/tests/specim_process.py
gref4hsi/tests/specim_process.py.orig
gref4hsi/tests/test_main_hi.py
gref4hsi/tests/test_main_uhi.py
gref4hsi/tests/test_multi_ray_trace.py
gref4hsi/tests/test_multi_ray_trace_no_pyembree.py
gref4hsi/utils/__init__.py
gref4hsi/utils/colours.py
gref4hsi/utils/config_utils.py
gref4hsi/utils/geometry_utils.py
gref4hsi/utils/gis_tools.py
gref4hsi/utils/parsing_utils.py
gref4hsi/utils/photogrammetry_utils.py
gref4hsi/utils/radiometry.py
gref4hsi/utils/specim_parsing_utils.py
gref4hsi/utils/uhi_parsing_utils.py
gref4hsi/utils/visualize.py
gref4hsi-0.2.4.dist-info/LICENCE.MD
gref4hsi-0.2.4.dist-info/METADATA
gref4hsi-0.2.4.dist-info/WHEEL
gref4hsi-0.2.4.dist-info/top_level.txt
gref4hsi-0.2.4.dist-info/RECORD
