Metadata-Version: 2.1
Name: gref4hsi
Version: 0.2.4
Summary: A Python package for for georeferencing and orthorectifying hyperspectral imagery
Home-page: https://github.com/havardlovas/gref4hsi
Author: Haavard Snefjellaa Loevaas
Author-email: havard.s.lovas@ntnu.no
License: EUPL-1.2
Classifier: Development Status :: 3 - Alpha
Classifier: Intended Audience :: Science/Research
Classifier: License :: OSI Approved :: European Union Public Licence 1.2 (EUPL 1.2)
Classifier: Operating System :: Microsoft :: Windows :: Windows 10
Classifier: Programming Language :: Python :: 3.8
Classifier: Programming Language :: Python :: 3.9
Classifier: Programming Language :: Python :: 3.10
Classifier: Programming Language :: Python :: 3.11
Classifier: Programming Language :: Python :: 3.12
Requires-Python: >3.7
License-File: LICENCE.MD
Requires-Dist: opencv-python
Requires-Dist: dill
Requires-Dist: geopandas
Requires-Dist: h5py
Requires-Dist: matplotlib
Requires-Dist: numpy
Requires-Dist: open3d
Requires-Dist: pandas
Requires-Dist: Pillow
Requires-Dist: pymap3d
Requires-Dist: pyproj
Requires-Dist: pyvista
Requires-Dist: pyvistaqt
Requires-Dist: scikit-learn
Requires-Dist: scipy
Requires-Dist: shapely
Requires-Dist: spectral
Requires-Dist: xmltodict
Requires-Dist: pykdtree
Requires-Dist: trimesh
Requires-Dist: rtree
Requires-Dist: embreex
Requires-Dist: ephem
